[{"__symbolic":"module","version":4,"metadata":{"EcommerceProductlistBestsellerComponent":{"__symbolic":"class","decorators":[{"__symbolic":"call","expression":{"__symbolic":"reference","module":"@angular/core","name":"Component","line":67,"character":1},"arguments":[{"selector":"app-ecommerce-productlist-bestseller","template":"\n<ion-list lines=\"none\">\n  <ion-item *ngFor=\"let item of databestseller.datas\" (click)=\"selectItemBestseller(item)\">\n    <ion-thumbnail slot=\"start\">\n      <img src=\"{{item.image.url}}\">\n    </ion-thumbnail>\n    <ion-label style=\"height:100%\">\n      <div padding-top>\n        <h2>{{item.name}}</h2>\n      </div>\n      <div padding-top>\n        <p class=\"weeklysales\">ยอดขายต่อสัปดาห์: {{item.weeklysales}}</p>\n        <div *ngIf=\"item.newpricetext === ''\">\n          <span class=\"colornewprice\">{{item.pricetext}}</span>\n        </div>\n\n        <div *ngIf=\"item.newpricetext !== ''\">\n          <span class=\"decoration-line\">{{item.pricetext}} </span><span class=\"colornewprice\">{{item.newpricetext}}</span>\n        </div>\n      </div>\n\n    </ion-label>\n  </ion-item>\n</ion-list>\n","styles":["\nion-item {\n  ion-thumbnail {\n      width: 30%;\n      height: 30%;\n  }\n  padding:6px;\n  margin: 10px;\n  border-radius: 10px;\n  background-color: #FFFFFF;\n  .decoration-line {\n      text-decoration-line: line-through; // color: #999;\n      color: rgba(0, 0, 0, .26); // font-size: 3.8vw;\n      font-size: 1.125rem;\n  }\n  h2 {\n      overflow: hidden;\n      text-overflow: ellipsis;\n      white-space: nowrap;\n      display: block;\n      width: 100%;\n      min-width: 1px; // font-size: 4.5vw\n      font-size: .995rem;\n      font-family: -apple-system, Helvetica Neue, Helvetica, Roboto, Droid Sans, Arial, sans-serif;\n      font-weight: 400;\n      height: 2.25rem;\n  }\n  .colornewprice {\n      // color: red; // font-size: 4vw;\n      font-size: 1.125rem;\n      color: #ff2600;\n      font-weight: 500;\n     \n  }\n  .weeklysales {\n      // font-size: 3.5vw;\n      font-size: .875rem;\n  }\n}\n"]}]}],"members":{"databestseller":[{"__symbolic":"property","decorators":[{"__symbolic":"call","expression":{"__symbolic":"reference","module":"@angular/core","name":"Input","line":74,"character":3}}]}],"outBestseller":[{"__symbolic":"property","decorators":[{"__symbolic":"call","expression":{"__symbolic":"reference","module":"@angular/core","name":"Output","line":75,"character":3}}]}],"__ctor__":[{"__symbolic":"constructor"}],"ngOnInit":[{"__symbolic":"method"}],"selectItemBestseller":[{"__symbolic":"method"}]}}}}]